ksconf_jinja_markdown.py
ksconf/plugins/jinja_markdown.py
ksconf_jinja_markdown-1.2.0.dist-info/METADATA
ksconf_jinja_markdown-1.2.0.dist-info/WHEEL
ksconf_jinja_markdown-1.2.0.dist-info/entry_points.txt
ksconf_jinja_markdown-1.2.0.dist-info/top_level.txt
ksconf_jinja_markdown-1.2.0.dist-info/RECORD
