Metadata-Version: 2.1
Name: ksconf-jinja-markdown
Version: 1.2.0
Summary: Markdown rendering support for Jinja2 templates within Ksconf
Home-page: https://github.com/Kintyre/ksconf/tree/devel/plugins/jinja-markdown
Author: Lowell Alleman
Author-email: lowell.alleman@cdillc.com
License: UNKNOWN
Keywords: ksconf splunk jinja markdown
Platform: UNKNOWN
Classifier: Development Status :: 5 - Production/Stable
Classifier: License :: OSI Approved :: Apache Software License
Classifier: Natural Language :: English
Classifier: Environment :: Plugins
Classifier: Topic :: Text Processing :: Markup
Classifier: Programming Language :: Python :: 3
Requires-Dist: commonmark >=0.9
Requires-Dist: jinja2 >=3.0
Requires-Dist: ksconf >=0.13.0
